<?xml version="1.0" encoding="UTF-8"?>
<!--
 ! Project home: https://github.com/jaxio/celerio-angular-quickstart
 ! 
 ! Source code generated by Celerio, an Open Source code generator by Jaxio.
 ! Documentation: http://www.jaxio.com/documentation/celerio/
 ! Modificado por CARLOS BAZALAR
 ! Email: cbazalarlarosa@gmail.com
 ! Template pack-angular:src/main/java/mapper/EntityXMLMapper.xml.e.vm
-->

<!DOCTYPE mapper PUBLIC "-//mybatis.org//DTD Mapper 3.0//EN" "http://mybatis.org/dtd/mybatis-3-mapper.dtd">

<mapper namespace="com.incloud.hcp.mapper.ItemMapper">

<resultMap id="itemResultMap" type="com.incloud.hcp.domain.Item">
	<id property="id" jdbcType="INTEGER" column="ID_ITEM" />
	<result property="descripcion" jdbcType="VARCHAR" column="DESCRIPCION" />	
	<result property="cantidad" jdbcType="INTEGER" column="CANTIDAD" />
	<result property="precioUnitario" jdbcType="NUMERIC" column="PRECIO_UNITARIO" />
	<result property="idBole.id" jdbcType="INTEGER" column="ID_BOLETA" />
</resultMap>


<select id="getLista" parameterType="com.incloud.hcp.domain.Item" resultMap="itemResultMap">
	SELECT 
      ID_ITEM , 
      DESCRIPCION , 
      CANTIDAD , 
      PRECIO_UNITARIO , 
      ID_BOLETA 
	FROM
	ITEM
	WHERE 1 = 1
	<if test="id != null ">
		AND ID_ITEM = #{id, jdbcType=INTEGER}
	</if>	
	<if test="descripcion != null and descripcion != '' ">
		AND DESCRIPCION = #{descripcion}
	</if>	
	<if test="cantidad != null ">
		AND CANTIDAD = #{cantidad, jdbcType=INTEGER}
	</if>	
	<if test="precioUnitario != null ">
		AND PRECIO_UNITARIO = #{precioUnitario, jdbcType=NUMERIC}
	</if>	
	<if test="idBole != null and idBole.id != null">
		AND ID_BOLETA = #{idBole.id, jdbcType=INTEGER}
	</if>	
</select>

<insert id="insertBean" >
INSERT INTO  ITEM(
ID_ITEM , 
DESCRIPCION , 
CANTIDAD , 
PRECIO_UNITARIO , 
ID_BOLETA 
)
VALUES
(
#{id} , 
#{descripcion} , 
#{cantidad} , 
#{precioUnitario} , 
#{idBole.id} 
)

</insert>

<insert id="insertMap" parameterType="java.util.Map" >
INSERT INTO  ITEM(
ID_ITEM , 
DESCRIPCION , 
CANTIDAD , 
PRECIO_UNITARIO , 
ID_BOLETA 
)
(
<foreach collection="list" item="element" index="index" separator=" UNION ">  
SELECT
#{element.id} , 
#{element.descripcion} , 
#{element.cantidad} , 
#{element.precioUnitario} , 
#{element.idBole.id} 
from dual

</foreach>    
)

</insert>


<update id="updateBean">
    UPDATE ITEM
    <set>
	<if test="descripcion != null and descripcion != '' ">
		DESCRIPCION = #{descripcion},
	</if>	
	<if test="cantidad != null ">
		CANTIDAD = #{cantidad, jdbcType=INTEGER},
	</if>	
	<if test="precioUnitario != null ">
		PRECIO_UNITARIO = #{precioUnitario, jdbcType=NUMERIC},
	</if>	
	<if test="idBoleta != null ">
		ID_BOLETA = #{idBole.id, jdbcType=INTEGER},
	</if>	
    </set> 
	WHERE 
	  ID_ITEM = #{id, jdbcType=INTEGER}	
</update>


<delete id="deleteBean">
    DELETE FROM ITEM
	WHERE 1 = 1
	<if test="id != null ">
		AND ID_ITEM = #{id, jdbcType=INTEGER}
	</if>	
	<if test="descripcion != null and descripcion != '' ">
		AND DESCRIPCION = #{descripcion}
	</if>	
	<if test="cantidad != null ">
		AND CANTIDAD = #{cantidad, jdbcType=INTEGER}
	</if>	
	<if test="precioUnitario != null ">
		AND PRECIO_UNITARIO = #{precioUnitario, jdbcType=NUMERIC}
	</if>	
	<if test="idBole != null and idBole.id != null">
		AND ID_BOLETA = #{idBole.id}
	</if>	
</delete>

<delete id="deleteAll">
   DELETE FROM ITEM
</delete>

</mapper>